anoptions/__init__.py
anoptions/baseoptions.py
anoptions/env.py
anoptions/exceptions.py
anoptions/options.py
anoptions/parameter.py
anoptions/typedoptions.py
anoptions/types.py
anoptions-2.0.0.dist-info/LICENSE
anoptions-2.0.0.dist-info/METADATA
anoptions-2.0.0.dist-info/WHEEL
anoptions-2.0.0.dist-info/top_level.txt
anoptions-2.0.0.dist-info/RECORD
