Metadata-Version: 2.1
Name: anoptions
Version: 2.0.0
Summary: Module to assist in defining application options and collecting user input for them from command line and environment variables
Author-email: Antti Nilsson <muut.py@antion.fi>
Classifier: Programming Language :: Python :: 3
Classifier: License :: OSI Approved :: MIT License
Classifier: Operating System :: OS Independent
Requires-Python: >=3.8
License-File: LICENSE
Requires-Dist: pydantic
